yacd/__init__.py
yacd/_yacd.py
yacd-2025.8.30.0.dist-info/METADATA
yacd-2025.8.30.0.dist-info/WHEEL
yacd-2025.8.30.0.dist-info/top_level.txt
yacd-2025.8.30.0.dist-info/RECORD
