Metadata-Version: 2.4
Name: yacd
Version: 2025.8.30.0
Summary: Yet Another Collection of Decorators
Author-email: Ann T Ropea <bedhanger@gmx.de>
License-Expression: MIT
Project-URL: Homepage, https://gitlab.com/bedhanger/mwe/-/tree/master/python/yacd
